{
  "version": "1.0.0",
  "appName": "TheraLog",
  "privacyUrl": "kebijakan-privasi.html",
  "termsUrl": "syarat-ketentuan.html",
  "description": "Aplikasi pencatat sesi terapi untuk terapis Amarta-Refleksi & Rumah Spa",
  "developer": "Toms Droid",
  "email": "droidtoms@gmail.com",
  "website": "https://theralogapp.vercel.app",
  "social": [
    { "name": "Instagram", "icon": "bi-instagram", "url": "https://instagram.com/tomsdroid" },
    { "name": "WhatsApp", "icon": "bi-whatsapp", "url": "https://wa.me/62895350422012?text=Halo Admin TheraLog!!" }
  ],
  "features": [
    "Input data offline",
    "Statistik otomatis", 
    "Sinkronisasi cloud"
  ]
}